repository_mongodb/__init__.py
repository_mongodb/base_model.py
repository_mongodb/base_repository.py
repository_mongodb/metaclasses.py
repository_mongodb/mongo_client.py
repository_mongodb/mongo_config.py
repository_mongodb/singleton_repository_metaclass.py
repository_mongodb/transaction_management.py
repository_mongodb/transaction_metaclass.py
tests/__init__.py
tests/conftest.py
tests/test_base_repository.py
repository_mongodb-0.1.8.dist-info/METADATA
repository_mongodb-0.1.8.dist-info/WHEEL
repository_mongodb-0.1.8.dist-info/top_level.txt
repository_mongodb-0.1.8.dist-info/RECORD
