Metadata-Version: 2.1
Name: repository-mongodb
Version: 0.1.8
Summary: A small library to simplify MongoDB usage with repository pattern
Home-page: https://github.com/ryan-zheng-teki/repository_mongodb
Author: Ryan Zheng
Author-email: ryan.zheng.work@gmail.com
Classifier: Development Status :: 3 - Alpha
Classifier: Intended Audience :: Developers
Classifier: License :: OSI Approved :: MIT License
Classifier: Programming Language :: Python :: 3.10
Requires-Python: >=3.9
Requires-Dist: pymongo >=4.8.0
Provides-Extra: dev
Requires-Dist: pytest >=7.3.1 ; extra == 'dev'
Requires-Dist: pytest-asyncio >=0.21.0 ; extra == 'dev'
